scikit_cache/__init__.py
scikit_cache/__version__.py
scikit_cache/components/__init__.py
scikit_cache/components/cleanup.py
scikit_cache/components/decorators.py
scikit_cache/components/estimators.py
scikit_cache/components/file_handler.py
scikit_cache/components/internal_cache.py
scikit_cache/components/logging.py
scikit_cache/controller.py
scikit_cache/py.typed
scikit_cache/resources.py
scikit_cache/utils/__init__.py
scikit_cache/utils/base.py
scikit_cache/utils/estimators.py
scikit_cache/utils/file_utils.py
scikit_cache/utils/hashing.py
scikit_cache/utils/output.py
scikit_cache/utils/versioning.py
scikit_cache-0.1.2.dist-info/WHEEL
scikit_cache-0.1.2.dist-info/METADATA
scikit_cache-0.1.2.dist-info/licenses/LICENSE
scikit_cache-0.1.2.dist-info/RECORD
