Metadata-Version: 2.1
Name: scikit_cache
Version: 0.1.2
Summary: Pickle-based caching library with SKLearn estimators supports
License: MIT
Author-email: Denis Krumko <dkrumko@gmail.ru>
Requires-Python: >=3.8
Classifier: Development Status :: 4 - Beta
Classifier: Environment :: Console
Classifier: Intended Audience :: Developers
Classifier: License :: OSI Approved :: MIT License
Classifier: Natural Language :: English
Classifier: Programming Language :: Python
Classifier: Programming Language :: Python :: 3
Classifier: Programming Language :: Python :: 3.10
Classifier: Programming Language :: Python :: 3.11
Classifier: Programming Language :: Python :: 3.8
Classifier: Programming Language :: Python :: 3.9
Classifier: Programming Language :: Python :: Implementation :: CPython
Classifier: Topic :: Software Development :: Libraries
Classifier: Topic :: Utilities
Requires-Dist: joblib
Requires-Dist: pydantic<=1.10.10
Requires-Dist: pyyaml
Provides-Extra: dev
Requires-Dist: flake8-pyproject; extra == "dev"
Requires-Dist: flake8-commas; extra == "dev"
Requires-Dist: flake8-isort!=5.0.1,!=5.0.2; extra == "dev"
Requires-Dist: flake8-bugbear; extra == "dev"
Requires-Dist: flake8-simplify; extra == "dev"
Requires-Dist: flake8-print; extra == "dev"
Requires-Dist: flake8-debugger; extra == "dev"
Requires-Dist: isort; extra == "dev"
Requires-Dist: mypy; extra == "dev"
Requires-Dist: pytest; extra == "dev"
Requires-Dist: pytest-mock; extra == "dev"
Requires-Dist: pytest-cov; extra == "dev"
Requires-Dist: coverage[toml]; extra == "dev"
Requires-Dist: pandas; extra == "dev"
Requires-Dist: scikit-learn>=1.1; extra == "dev"
Requires-Dist: requests==2.27.1; extra == "dev"
Requires-Dist: werkzeug==2.0.0; extra == "dev"
Project-URL: repository, https://github.com/deniskrumko/scikit-cache
